{"name": "Bod\u00f8", "children": [{"name": "society", "children": [{"name": "education", "children": [{"name": "students ict access", "score": 14.860946016796884, "targetAvailable": 0}, {"name": "school enrollment", "score": 36.73383308486624, "targetAvailable": 0}, {"name": "higher education degrees", "score": 14.328077538371387, "targetAvailable": 0}, {"name": "adult literacy", "score": 17.539391569021255, "targetAvailable": 0}], "targetAvailable": 0, "score": 20.86556205226394}, {"name": "health", "children": [{"name": "electronic health records", "score": 34.696941687403815, "targetAvailable": 0}, {"name": "life expectancy", "score": 72.43595509038461, "targetAvailable": 0}, {"name": "maternal mortality rate", "score": 20.79758569305392, "targetAvailable": 0}, {"name": "doctors", "score": 83.27462482745061, "targetAvailable": 0}, {"name": "health insurance coverage", "score": 66.99193717253266, "targetAvailable": 0}, {"name": "in-patient hospital beds", "score": 69.19896849960743, "targetAvailable": 0}], "targetAvailable": 0, "score": 57.89933549507217}, {"name": "culture", "children": [{"name": "cultural expenditure", "score": 98.44927522292684, "targetAvailable": 0}, {"name": "cultural infrastructure", "score": 23.383090373365047, "targetAvailable": 0}], "targetAvailable": 0, "score": 60.91618279814595}, {"name": "housing", "children": [{"name": "informal settlements", "score": 70.66047169555686, "targetAvailable": 0}, {"name": "housing expenditure", "score": 24.786923578005016, "targetAvailable": 0}], "targetAvailable": 0, "score": 47.72369763678094}, {"name": "social inclusion", "children": [{"name": "gender income equity", "score": 19.40511087270419, "targetAvailable": 0}, {"name": "gini coefficient", "score": 32.22357704420029, "targetAvailable": 0}, {"name": "poverty", "score": 45.06057988194434, "targetAvailable": 0}, {"name": "voter participation", "score": 18.82254339342496, "targetAvailable": 0}, {"name": "child care availability", "score": 99.07190040373514, "targetAvailable": 0}], "targetAvailable": 0, "score": 42.91674231920179}, {"name": "safety", "children": [{"name": "natural disaster related deaths", "score": 4.271256303928494, "targetAvailable": 0}, {"name": "disaster related economic losses", "score": 91.111841517908, "targetAvailable": 0}, {"name": "resilience plans", "score": 62.26915212210833, "targetAvailable": 0}, {"name": "at risk population", "score": 80.4416682557651, "targetAvailable": 0}, {"name": "Emergency service response time", "score": 94.39037679755418, "targetAvailable": 0}, {"name": "police service", "score": 85.5766438273354, "targetAvailable": 0}, {"name": "fire service", "score": 85.71372154793615, "targetAvailable": 0}, {"name": "violent crime rate", "score": 35.03610371720956, "targetAvailable": 0}, {"name": "transportation fatalities", "score": 63.250741877803165, "targetAvailable": 0}], "targetAvailable": 0, "score": 66.89572288528316}, {"name": "food security", "children": [{"name": "local food production", "score": 51.83149923072814, "targetAvailable": 0}], "targetAvailable": 0, "score": 51.83149923072814}], "targetAvailable": 0, "score": 49.86410605963944}, {"name": "economy", "children": [{"name": "ict infrastructure", "children": [{"name": "household internet access", "score": 61.0651909293626, "targetAvailable": 0}, {"name": "fixed broadband subscriptions", "score": 32.66269358878847, "targetAvailable": 0}, {"name": "wireless broadband subscription", "score": 79.76161334547585, "targetAvailable": 0}, {"name": "wireless broadband coverage 3G", "score": 89.78346128799483, "targetAvailable": 0}, {"name": "wireless broadband coverage 4G", "score": 83.43879053615039, "targetAvailable": 0}, {"name": "availability of wifi in public areas", "score": 74.5280385938188, "targetAvailable": 0}], "targetAvailable": 0, "score": 70.20663138026516}, {"name": "water and sanitation", "children": [{"name": "smart water meters", "score": 7.195906915188333, "targetAvailable": 0}, {"name": "water supply ict monitoring", "score": 65.67705129327366, "targetAvailable": 0}, {"name": "basic water supply", "score": 94.58352751841969, "targetAvailable": 0}, {"name": "potable water supply", "score": 45.758689369788875, "targetAvailable": 0}, {"name": "water supply loss", "score": 19.47804941614246, "targetAvailable": 0}, {"name": "wastewater collection", "score": 70.76359985916528, "targetAvailable": 0}, {"name": "household sanitation", "score": 64.38872156764181, "targetAvailable": 0}], "targetAvailable": 0, "score": 52.54936370566002}, {"name": "drainage", "children": [{"name": "drainage / storm water system ict monitoring", "score": 13.879101158297125, "targetAvailable": 0}], "targetAvailable": 0, "score": 13.879101158297125}, {"name": "electricity supply", "children": [{"name": "smart electricity meters", "score": 89.29781710197398, "targetAvailable": 0}, {"name": "electricity supply ict monitoring", "score": 87.06907938763584, "targetAvailable": 0}, {"name": "demand response penetration", "score": 2.574329542498699, "targetAvailable": 0}, {"name": "electricity system outage frequency", "score": 92.37700400059379, "targetAvailable": 0}, {"name": "electricity system outage time", "score": 24.310926923692257, "targetAvailable": 0}, {"name": "access to electricity", "score": 32.054854304529755, "targetAvailable": 0}], "targetAvailable": 0, "score": 54.614001876820716}, {"name": "transport", "children": [{"name": "dynamic public transport information", "score": 72.46287740796767, "targetAvailable": 0}, {"name": "traffic monitoring", "score": 71.40641883967005, "targetAvailable": 0}, {"name": "intersection control", "score": 7.348043664386372, "targetAvailable": 0}, {"name": "public transit network", "score": 62.64398316027865, "targetAvailable": 0}, {"name": "public transit network convenience", "score": 30.485318660388028, "targetAvailable": 0}, {"name": "bicycle network", "score": 86.00083213917308, "targetAvailable": 0}, {"name": "transportation mode share private vehicles", "score": 60.34819774570771, "targetAvailable": 0}, {"name": "transportation mode share public transport", "score": 4.317945528711431, "targetAvailable": 0}, {"name": "transportation mode share walking", "score": 47.13745898844744, "targetAvailable": 0}, {"name": "transportation mode share cycling", "score": 66.08448597397683, "targetAvailable": 0}, {"name": "transportation mode share paratransport", "score": 65.98380932560887, "targetAvailable": 0}, {"name": "travel time index", "score": 66.49331280790643, "targetAvailable": 0}, {"name": "shared bicycles", "score": 67.47129475143353, "targetAvailable": 0}, {"name": "shared vehicles", "score": 60.54614207807742, "targetAvailable": 0}, {"name": "low-carbon emission vehicles", "score": 69.21157365139476, "targetAvailable": 0}], "targetAvailable": 0, "score": 55.86277964820856}, {"name": "public service", "children": [{"name": "open data sets published", "score": 1.3806434771947096, "targetAvailable": 0}, {"name": "open data sets %", "score": 36.60959474647416, "targetAvailable": 0}, {"name": "e-government", "score": 7.908257897978832, "targetAvailable": 0}, {"name": "public sector e-procurement", "score": 63.11126638834133, "targetAvailable": 0}], "targetAvailable": 0, "score": 27.252440627497258}, {"name": "innovation", "children": [{"name": "R&D expenditure", "score": 51.26883555078695, "targetAvailable": 0}, {"name": "patents", "score": 15.463352238470263, "targetAvailable": 0}, {"name": "small and medium-sized enterprises", "score": 41.01518591882678, "targetAvailable": 0}], "targetAvailable": 0, "score": 35.91579123602799}, {"name": "employment", "children": [{"name": "unemployment rate", "score": 30.694066928569807, "targetAvailable": 0}, {"name": "youth unemployment rate", "score": 13.21281602560449, "targetAvailable": 0}, {"name": "tourism industry employment", "score": 75.7722034364694, "targetAvailable": 0}, {"name": "ict industry employment", "score": 2.3919874789688933, "targetAvailable": 0}], "targetAvailable": 0, "score": 30.517768467403144}, {"name": "waste", "children": [{"name": "solid waste collection", "score": 62.12167345246093, "targetAvailable": 0}], "targetAvailable": 0, "score": 62.12167345246093}, {"name": "buildings", "children": [{"name": "public building sustainability", "score": 21.922424604351008, "targetAvailable": 0}, {"name": "integrated building management systems", "score": 31.43959003065221, "targetAvailable": 0}], "targetAvailable": 0, "score": 26.68100731750161}, {"name": "urban planning", "children": [{"name": "pedestrian infrastructure", "score": 35.47125962841026, "targetAvailable": 0}, {"name": "urban development and spatial planning", "score": 30.724008304525054, "targetAvailable": 0}], "targetAvailable": 0, "score": 33.097633966467654}], "targetAvailable": 0, "score": 42.06347207605547}, {"name": "environment", "children": [{"name": "air quality", "children": [{"name": "air pollution PM2.5", "score": 93.04052685487669, "targetAvailable": 0}, {"name": "air pollution PM10", "score": 99.94805393023344, "targetAvailable": 0}, {"name": "air pollution NO2", "score": 80.00613660249101, "targetAvailable": 0}, {"name": "air pollution SO2", "score": 34.22136585035472, "targetAvailable": 0}, {"name": "air pollution O3", "score": 84.36095457022654, "targetAvailable": 0}, {"name": "ghg emissions", "score": 7.410298321380382, "targetAvailable": 0}], "targetAvailable": 0, "score": 66.49788935492712}, {"name": "waster and sanitation", "children": [{"name": "drinking water quality", "score": 32.80446077336697, "targetAvailable": 0}, {"name": "water consumption", "score": 33.716122249419925, "targetAvailable": 0}, {"name": "fresh water consumption", "score": 76.23094217984764, "targetAvailable": 0}, {"name": "wastewater treated primary", "score": 46.44163640960185, "targetAvailable": 0}, {"name": "wastewater treated secondary", "score": 31.74152732354306, "targetAvailable": 0}, {"name": "wastewater treated tertiary", "score": 54.60266049724706, "targetAvailable": 0}], "targetAvailable": 0, "score": 45.92289157217109}, {"name": "environmental waste", "children": [{"name": "solid waste treatment landfill", "score": 69.42378353648415, "targetAvailable": 0}, {"name": "solid waste treatment burnt", "score": 31.431418208539007, "targetAvailable": 0}, {"name": "solid waste treatment incinerated", "score": 74.45565841208357, "targetAvailable": 0}, {"name": "solid waste treatment recycled", "score": 70.32879253454763, "targetAvailable": 0}, {"name": "solid waste treatment other", "score": 28.592344307451924, "targetAvailable": 0}, {"name": "solid waste treatment open dump", "score": 25.037136461378783, "targetAvailable": 0}], "targetAvailable": 0, "score": 49.878188910080844}, {"name": "environment quality", "children": [{"name": "emf exposure", "score": 83.50493916953535, "targetAvailable": 0}, {"name": "noise exposure", "score": 84.40876585843957, "targetAvailable": 0}], "targetAvailable": 0, "score": 83.95685251398746}, {"name": "public space and nature", "children": [{"name": "green areas", "score": 78.25838114851344, "targetAvailable": 0}, {"name": "green area accessibility", "score": 53.21096525360358, "targetAvailable": 0}, {"name": "protected areas", "score": 93.80200279784863, "targetAvailable": 0}, {"name": "recreational facilities", "score": 63.654554564047494, "targetAvailable": 0}], "targetAvailable": 0, "score": 72.23147594100328}, {"name": "energy", "children": [{"name": "renewable energy consumption", "score": 84.06808176967722, "targetAvailable": 0}, {"name": "electricity consumption", "score": 37.92679229218082, "targetAvailable": 0}, {"name": "residential thermal energy consumption", "score": 50.69386022581984, "targetAvailable": 0}, {"name": "public building energy consumption", "score": 12.055146087791169, "targetAvailable": 0}], "targetAvailable": 0, "score": 46.18597009386726}], "targetAvailable": 0, "score": 60.7788780643395}], "targetAvailable": 0, "score": 50.902152066678134}