{"name": "Molde", "children": [{"name": "society", "children": [{"name": "education", "children": [{"name": "students ict access", "score": 84.03280855378156, "targetAvailable": 0}, {"name": "school enrollment", "score": 10.918153326720237, "targetAvailable": 0}, {"name": "higher education degrees", "score": 50.5816746328009, "targetAvailable": 0}, {"name": "adult literacy", "score": 88.35215690490935, "targetAvailable": 0}], "targetAvailable": 0, "score": 58.47119835455301}, {"name": "health", "children": [{"name": "electronic health records", "score": 70.68560671673116, "targetAvailable": 0}, {"name": "life expectancy", "score": 18.29955622536876, "targetAvailable": 0}, {"name": "maternal mortality rate", "score": 52.79584458847728, "targetAvailable": 0}, {"name": "doctors", "score": 19.62244142653853, "targetAvailable": 0}, {"name": "health insurance coverage", "score": 41.69613510744404, "targetAvailable": 0}, {"name": "in-patient hospital beds", "score": 93.72559941500762, "targetAvailable": 0}], "targetAvailable": 0, "score": 49.47086391326123}, {"name": "culture", "children": [{"name": "cultural expenditure", "score": 19.731759464944744, "targetAvailable": 0}, {"name": "cultural infrastructure", "score": 47.22998818596915, "targetAvailable": 0}], "targetAvailable": 0, "score": 33.480873825456946}, {"name": "housing", "children": [{"name": "informal settlements", "score": 46.47741012056085, "targetAvailable": 0}, {"name": "housing expenditure", "score": 62.767873730511006, "targetAvailable": 0}], "targetAvailable": 0, "score": 54.62264192553593}, {"name": "social inclusion", "children": [{"name": "gender income equity", "score": 83.2331197549714, "targetAvailable": 0}, {"name": "gini coefficient", "score": 55.37980854742892, "targetAvailable": 0}, {"name": "poverty", "score": 7.1182594619155, "targetAvailable": 0}, {"name": "voter participation", "score": 98.98803658852945, "targetAvailable": 0}, {"name": "child care availability", "score": 70.95112484665862, "targetAvailable": 0}], "targetAvailable": 0, "score": 63.13406983990078}, {"name": "safety", "children": [{"name": "natural disaster related deaths", "score": 66.96191140519701, "targetAvailable": 0}, {"name": "disaster related economic losses", "score": 67.09351475224393, "targetAvailable": 0}, {"name": "resilience plans", "score": 94.89995108920783, "targetAvailable": 0}, {"name": "at risk population", "score": 75.31812396636221, "targetAvailable": 0}, {"name": "Emergency service response time", "score": 45.346950554142516, "targetAvailable": 0}, {"name": "police service", "score": 74.88112707653795, "targetAvailable": 0}, {"name": "fire service", "score": 56.07419163458766, "targetAvailable": 0}, {"name": "violent crime rate", "score": 90.28226199854399, "targetAvailable": 0}, {"name": "transportation fatalities", "score": 70.28982637544078, "targetAvailable": 0}], "targetAvailable": 0, "score": 71.23865098358488}, {"name": "food security", "children": [{"name": "local food production", "score": 97.06765561896577, "targetAvailable": 0}], "targetAvailable": 0, "score": 97.06765561896577}], "targetAvailable": 0, "score": 61.069422065894074}, {"name": "economy", "children": [{"name": "ict infrastructure", "children": [{"name": "household internet access", "score": 74.89463179932575, "targetAvailable": 0}, {"name": "fixed broadband subscriptions", "score": 33.067085677467475, "targetAvailable": 0}, {"name": "wireless broadband subscription", "score": 22.53683209170143, "targetAvailable": 0}, {"name": "wireless broadband coverage 3G", "score": 83.16054839237503, "targetAvailable": 0}, {"name": "wireless broadband coverage 4G", "score": 27.38232750039611, "targetAvailable": 0}, {"name": "availability of wifi in public areas", "score": 84.00404289191187, "targetAvailable": 0}], "targetAvailable": 0, "score": 54.17424472552961}, {"name": "water and sanitation", "children": [{"name": "smart water meters", "score": 38.30931456242105, "targetAvailable": 0}, {"name": "water supply ict monitoring", "score": 90.00927284553066, "targetAvailable": 0}, {"name": "basic water supply", "score": 12.374408232545619, "targetAvailable": 0}, {"name": "potable water supply", "score": 69.88578499592374, "targetAvailable": 0}, {"name": "water supply loss", "score": 97.82988977387897, "targetAvailable": 0}, {"name": "wastewater collection", "score": 20.845843509146288, "targetAvailable": 0}, {"name": "household sanitation", "score": 4.743644108967137, "targetAvailable": 0}], "targetAvailable": 0, "score": 47.71402257548764}, {"name": "drainage", "children": [{"name": "drainage / storm water system ict monitoring", "score": 3.024420645123105, "targetAvailable": 0}], "targetAvailable": 0, "score": 3.024420645123105}, {"name": "electricity supply", "children": [{"name": "smart electricity meters", "score": 78.88825107667033, "targetAvailable": 0}, {"name": "electricity supply ict monitoring", "score": 3.8993076870149967, "targetAvailable": 0}, {"name": "demand response penetration", "score": 49.91265215115995, "targetAvailable": 0}, {"name": "electricity system outage frequency", "score": 7.946376160768221, "targetAvailable": 0}, {"name": "electricity system outage time", "score": 9.98891114196432, "targetAvailable": 0}, {"name": "access to electricity", "score": 22.937811832067613, "targetAvailable": 0}], "targetAvailable": 0, "score": 28.928885008274236}, {"name": "transport", "children": [{"name": "dynamic public transport information", "score": 18.840811916348233, "targetAvailable": 0}, {"name": "traffic monitoring", "score": 66.5924980386887, "targetAvailable": 0}, {"name": "intersection control", "score": 52.227596412867925, "targetAvailable": 0}, {"name": "public transit network", "score": 15.079549726210962, "targetAvailable": 0}, {"name": "public transit network convenience", "score": 43.433629640230144, "targetAvailable": 0}, {"name": "bicycle network", "score": 0.4795494412528356, "targetAvailable": 0}, {"name": "transportation mode share private vehicles", "score": 68.96278609771362, "targetAvailable": 0}, {"name": "transportation mode share public transport", "score": 44.807556064944485, "targetAvailable": 0}, {"name": "transportation mode share walking", "score": 69.91042250771126, "targetAvailable": 0}, {"name": "transportation mode share cycling", "score": 94.7800914853158, "targetAvailable": 0}, {"name": "transportation mode share paratransport", "score": 79.51682432222152, "targetAvailable": 0}, {"name": "travel time index", "score": 73.28903987305004, "targetAvailable": 0}, {"name": "shared bicycles", "score": 83.49804804163514, "targetAvailable": 0}, {"name": "shared vehicles", "score": 73.57140342585762, "targetAvailable": 0}, {"name": "low-carbon emission vehicles", "score": 43.300308906959565, "targetAvailable": 0}], "targetAvailable": 0, "score": 55.21934106006719}, {"name": "public service", "children": [{"name": "open data sets published", "score": 74.9979972198398, "targetAvailable": 0}, {"name": "open data sets %", "score": 90.22420372302479, "targetAvailable": 0}, {"name": "e-government", "score": 96.01362085924185, "targetAvailable": 0}, {"name": "public sector e-procurement", "score": 35.54116288773933, "targetAvailable": 0}], "targetAvailable": 0, "score": 74.19424617246145}, {"name": "innovation", "children": [{"name": "R&D expenditure", "score": 93.99473754569414, "targetAvailable": 0}, {"name": "patents", "score": 39.44399268821556, "targetAvailable": 0}, {"name": "small and medium-sized enterprises", "score": 39.50676350753861, "targetAvailable": 0}], "targetAvailable": 0, "score": 57.6484979138161}, {"name": "employment", "children": [{"name": "unemployment rate", "score": 56.59061659592284, "targetAvailable": 0}, {"name": "youth unemployment rate", "score": 15.535371538405606, "targetAvailable": 0}, {"name": "tourism industry employment", "score": 96.61656176453172, "targetAvailable": 0}, {"name": "ict industry employment", "score": 17.28028439450977, "targetAvailable": 0}], "targetAvailable": 0, "score": 46.50570857334249}, {"name": "waste", "children": [{"name": "solid waste collection", "score": 12.301229668373303, "targetAvailable": 0}], "targetAvailable": 0, "score": 12.301229668373303}, {"name": "buildings", "children": [{"name": "public building sustainability", "score": 81.61277830181032, "targetAvailable": 0}, {"name": "integrated building management systems", "score": 91.06532221155307, "targetAvailable": 0}], "targetAvailable": 0, "score": 86.3390502566817}, {"name": "urban planning", "children": [{"name": "pedestrian infrastructure", "score": 3.497748093462183, "targetAvailable": 0}, {"name": "urban development and spatial planning", "score": 47.686624592500515, "targetAvailable": 0}], "targetAvailable": 0, "score": 25.59218634298135}], "targetAvailable": 0, "score": 44.69471208564892}, {"name": "environment", "children": [{"name": "air quality", "children": [{"name": "air pollution PM2.5", "score": 65.38482724450229, "targetAvailable": 0}, {"name": "air pollution PM10", "score": 54.784423916624505, "targetAvailable": 0}, {"name": "air pollution NO2", "score": 97.46183304804966, "targetAvailable": 0}, {"name": "air pollution SO2", "score": 73.54865155638305, "targetAvailable": 0}, {"name": "air pollution O3", "score": 22.190906878522465, "targetAvailable": 0}, {"name": "ghg emissions", "score": 78.91416125362719, "targetAvailable": 0}], "targetAvailable": 0, "score": 65.3808006496182}, {"name": "waster and sanitation", "children": [{"name": "drinking water quality", "score": 42.18648044280807, "targetAvailable": 0}, {"name": "water consumption", "score": 32.8067922252213, "targetAvailable": 0}, {"name": "fresh water consumption", "score": 1.7099597070213801, "targetAvailable": 0}, {"name": "wastewater treated primary", "score": 96.57045354093906, "targetAvailable": 0}, {"name": "wastewater treated secondary", "score": 47.11751287755137, "targetAvailable": 0}, {"name": "wastewater treated tertiary", "score": 20.352223454182482, "targetAvailable": 0}], "targetAvailable": 0, "score": 40.12390370795394}, {"name": "environmental waste", "children": [{"name": "solid waste treatment landfill", "score": 6.170979675633658, "targetAvailable": 0}, {"name": "solid waste treatment burnt", "score": 1.3411332995361236, "targetAvailable": 0}, {"name": "solid waste treatment incinerated", "score": 19.00968059028626, "targetAvailable": 0}, {"name": "solid waste treatment recycled", "score": 70.39985484486522, "targetAvailable": 0}, {"name": "solid waste treatment other", "score": 84.37980773743924, "targetAvailable": 0}, {"name": "solid waste treatment open dump", "score": 96.77810283232422, "targetAvailable": 0}], "targetAvailable": 0, "score": 46.34659316334745}, {"name": "environment quality", "children": [{"name": "emf exposure", "score": 16.203372957936825, "targetAvailable": 0}, {"name": "noise exposure", "score": 39.41775755788991, "targetAvailable": 0}], "targetAvailable": 0, "score": 27.810565257913368}, {"name": "public space and nature", "children": [{"name": "green areas", "score": 55.668309214975174, "targetAvailable": 0}, {"name": "green area accessibility", "score": 91.9653036126713, "targetAvailable": 0}, {"name": "protected areas", "score": 67.16601847959424, "targetAvailable": 0}, {"name": "recreational facilities", "score": 54.24433029120706, "targetAvailable": 0}], "targetAvailable": 0, "score": 67.26099039961196}, {"name": "energy", "children": [{"name": "renewable energy consumption", "score": 23.220629009339, "targetAvailable": 0}, {"name": "electricity consumption", "score": 81.82989807668814, "targetAvailable": 0}, {"name": "residential thermal energy consumption", "score": 54.992663569381584, "targetAvailable": 0}, {"name": "public building energy consumption", "score": 41.08308699656117, "targetAvailable": 0}], "targetAvailable": 0, "score": 50.281569412992475}], "targetAvailable": 0, "score": 49.53407043190623}], "targetAvailable": 0, "score": 51.766068194483076}