{"name": "B\u00e6rum", "children": [{"name": "society", "children": [{"name": "education", "children": [{"name": "students ict access", "score": 57.39076240715798, "targetAvailable": 0}, {"name": "school enrollment", "score": 50.7307902664185, "targetAvailable": 0}, {"name": "higher education degrees", "score": 47.89290993967597, "targetAvailable": 0}, {"name": "adult literacy", "score": 47.235069783157364, "targetAvailable": 0}], "score": 50.812383099102455, "targetAvailable": 0}, {"name": "health", "children": [{"name": "electronic health records", "score": 42.933788255566064, "targetAvailable": 0}, {"name": "life expectancy", "score": 43.33149240788759, "targetAvailable": 0}, {"name": "maternal mortality rate", "score": 45.253725914231644, "targetAvailable": 0}, {"name": "doctors", "score": 40.8245183107202, "targetAvailable": 0}, {"name": "health insurance coverage", "score": 41.47716979492615, "targetAvailable": 0}, {"name": "in-patient hospital beds", "score": 50.07994194432296, "targetAvailable": 0}], "score": 43.983439437942444, "targetAvailable": 0}, {"name": "culture", "children": [{"name": "cultural expenditure", "score": 53.1929532332904, "targetAvailable": 0}, {"name": "cultural infrastructure", "score": 47.770076455669546, "targetAvailable": 0}], "score": 50.48151484447997, "targetAvailable": 0}, {"name": "housing", "children": [{"name": "informal settlements", "score": 35.70708117482322, "targetAvailable": 0}, {"name": "housing expenditure", "score": 55.54339278589253, "targetAvailable": 0}], "score": 45.62523698035787, "targetAvailable": 0}, {"name": "social inclusion", "children": [{"name": "gender income equity", "score": 47.2668775707266, "targetAvailable": 0}, {"name": "gini coefficient", "score": 53.19757987284592, "targetAvailable": 0}, {"name": "poverty", "score": 66.8132532161101, "targetAvailable": 0}, {"name": "voter participation", "score": 59.18698089409295, "targetAvailable": 0}, {"name": "child care availability", "score": 52.05644987368572, "targetAvailable": 0}], "score": 55.704228285492256, "targetAvailable": 0}, {"name": "safety", "children": [{"name": "natural disaster related deaths", "score": 42.26642069513653, "targetAvailable": 0}, {"name": "disaster related economic losses", "score": 47.87011169288493, "targetAvailable": 0}, {"name": "resilience plans", "score": 45.24653546001792, "targetAvailable": 0}, {"name": "at risk population", "score": 41.935686595514355, "targetAvailable": 0}, {"name": "Emergency service response time", "score": 57.84256562054069, "targetAvailable": 0}, {"name": "police service", "score": 36.21953179268741, "targetAvailable": 0}, {"name": "fire service", "score": 44.85220502410949, "targetAvailable": 0}, {"name": "violent crime rate", "score": 39.94573881409292, "targetAvailable": 0}, {"name": "transportation fatalities", "score": 55.51831191248858, "targetAvailable": 0}], "score": 45.74412306749698, "targetAvailable": 0}, {"name": "food security", "children": [{"name": "local food production", "score": 57.11834638050635, "targetAvailable": 0}], "score": 57.11834638050635, "targetAvailable": 0}], "score": 49.9241817279112, "targetAvailable": 0}, {"name": "economy", "children": [{"name": "ict infrastructure", "children": [{"name": "household internet access", "score": 44.72657683649391, "targetAvailable": 0}, {"name": "fixed broadband subscriptions", "score": 45.9775562915039, "targetAvailable": 0}, {"name": "wireless broadband subscription", "score": 64.40290615935756, "targetAvailable": 0}, {"name": "wireless broadband coverage 3G", "score": 69.73172783857221, "targetAvailable": 0}, {"name": "wireless broadband coverage 4G", "score": 53.86884161345188, "targetAvailable": 0}, {"name": "availability of wifi in public areas", "score": 54.6337591059785, "targetAvailable": 0}], "score": 55.556894640892985, "targetAvailable": 0}, {"name": "water and sanitation", "children": [{"name": "smart water meters", "score": 50.092314171613985, "targetAvailable": 0}, {"name": "water supply ict monitoring", "score": 44.39089828976645, "targetAvailable": 0}, {"name": "basic water supply", "score": 40.22280302689283, "targetAvailable": 0}, {"name": "potable water supply", "score": 42.46266523792496, "targetAvailable": 0}, {"name": "water supply loss", "score": 43.090442374570294, "targetAvailable": 0}, {"name": "wastewater collection", "score": 38.077615555824245, "targetAvailable": 0}, {"name": "household sanitation", "score": 50.32313404157319, "targetAvailable": 0}], "score": 44.094267528309416, "targetAvailable": 0}, {"name": "drainage", "children": [{"name": "drainage / storm water system ict monitoring", "score": 50.565540271073594, "targetAvailable": 0}], "score": 50.565540271073594, "targetAvailable": 0}, {"name": "electricity supply", "children": [{"name": "smart electricity meters", "score": 37.71475310374878, "targetAvailable": 0}, {"name": "electricity supply ict monitoring", "score": 45.19719761923995, "targetAvailable": 0}, {"name": "demand response penetration", "score": 48.04323608149954, "targetAvailable": 0}, {"name": "electricity system outage frequency", "score": 42.45514560369008, "targetAvailable": 0}, {"name": "electricity system outage time", "score": 58.90136015345529, "targetAvailable": 0}, {"name": "access to electricity", "score": 44.7269953909518, "targetAvailable": 0}], "score": 46.17311465876424, "targetAvailable": 0}, {"name": "transport", "children": [{"name": "dynamic public transport information", "score": 52.92344052281067, "targetAvailable": 0}, {"name": "traffic monitoring", "score": 40.93077091505887, "targetAvailable": 0}, {"name": "intersection control", "score": 42.86556201406622, "targetAvailable": 0}, {"name": "public transit network", "score": 51.56688852505669, "targetAvailable": 0}, {"name": "public transit network convenience", "score": 46.01360003975589, "targetAvailable": 0}, {"name": "bicycle network", "score": 44.87966403521309, "targetAvailable": 0}, {"name": "transportation mode share private vehicles", "score": 23.50481312266129, "targetAvailable": 0}, {"name": "transportation mode share public transport", "score": 53.75783104418434, "targetAvailable": 0}, {"name": "transportation mode share walking", "score": 42.6776491167669, "targetAvailable": 0}, {"name": "transportation mode share cycling", "score": 39.82868537673958, "targetAvailable": 0}, {"name": "transportation mode share paratransport", "score": 36.5681978676981, "targetAvailable": 0}, {"name": "travel time index", "score": 59.46386938469043, "targetAvailable": 0}, {"name": "shared bicycles", "score": 49.78809766104177, "targetAvailable": 0}, {"name": "shared vehicles", "score": 49.46904814700153, "targetAvailable": 0}, {"name": "low-carbon emission vehicles", "score": 36.90432357657901, "targetAvailable": 0}], "score": 44.74282942328829, "targetAvailable": 0}, {"name": "public service", "children": [{"name": "open data sets published", "score": 58.34818344443088, "targetAvailable": 0}, {"name": "open data sets %", "score": 52.86582134324015, "targetAvailable": 0}, {"name": "e-government", "score": 31.310946332967394, "targetAvailable": 0}, {"name": "public sector e-procurement", "score": 47.763855065700376, "targetAvailable": 0}], "score": 47.5722015465847, "targetAvailable": 0}, {"name": "innovation", "children": [{"name": "R&D expenditure", "score": 59.19630793216762, "targetAvailable": 0}, {"name": "patents", "score": 58.386898579672014, "targetAvailable": 0}, {"name": "small and medium-sized enterprises", "score": 51.54561988855799, "targetAvailable": 0}], "score": 56.37627546679921, "targetAvailable": 0}, {"name": "employment", "children": [{"name": "unemployment rate", "score": 46.0265193334844, "targetAvailable": 0}, {"name": "youth unemployment rate", "score": 42.815221099720254, "targetAvailable": 0}, {"name": "tourism industry employment", "score": 49.35247653162523, "targetAvailable": 0}, {"name": "ict industry employment", "score": 44.943686990422485, "targetAvailable": 0}], "score": 45.78447598881309, "targetAvailable": 0}, {"name": "waste", "children": [{"name": "solid waste collection", "score": 52.0813845529151, "targetAvailable": 0}], "score": 52.0813845529151, "targetAvailable": 0}, {"name": "buildings", "children": [{"name": "public building sustainability", "score": 51.29590209592453, "targetAvailable": 0}, {"name": "integrated building management systems", "score": 55.15504973960827, "targetAvailable": 0}], "score": 53.2254759177664, "targetAvailable": 0}, {"name": "urban planning", "children": [{"name": "pedestrian infrastructure", "score": 61.578265011576114, "targetAvailable": 0}, {"name": "urban development and spatial planning", "score": 49.2684019226254, "targetAvailable": 0}], "score": 55.42333346710075, "targetAvailable": 0}], "score": 50.14507213293707, "targetAvailable": 0}, {"name": "environment", "children": [{"name": "air quality", "children": [{"name": "air pollution PM2.5", "score": 44.21073829884407, "targetAvailable": 0}, {"name": "air pollution PM10", "score": 45.98575197635609, "targetAvailable": 0}, {"name": "air pollution NO2", "score": 47.91746803311031, "targetAvailable": 0}, {"name": "air pollution SO2", "score": 54.589436676830594, "targetAvailable": 0}, {"name": "air pollution O3", "score": 61.2307987934974, "targetAvailable": 0}, {"name": "ghg emissions", "score": 54.012392990456654, "targetAvailable": 0}], "score": 51.32443112818253, "targetAvailable": 0}, {"name": "waster and sanitation", "children": [{"name": "drinking water quality", "score": 31.987428924226748, "targetAvailable": 0}, {"name": "water consumption", "score": 41.413534840625005, "targetAvailable": 0}, {"name": "fresh water consumption", "score": 59.323656750332, "targetAvailable": 0}, {"name": "wastewater treated primary", "score": 67.44286911742914, "targetAvailable": 0}, {"name": "wastewater treated secondary", "score": 51.248728285239224, "targetAvailable": 0}, {"name": "wastewater treated tertiary", "score": 46.67746115088292, "targetAvailable": 0}], "score": 49.68227984478917, "targetAvailable": 0}, {"name": "environmental waste", "children": [{"name": "solid waste treatment landfill", "score": 45.70201280250084, "targetAvailable": 0}, {"name": "solid waste treatment burnt", "score": 51.605537934529345, "targetAvailable": 0}, {"name": "solid waste treatment incinerated", "score": 55.07738974590385, "targetAvailable": 0}, {"name": "solid waste treatment recycled", "score": 42.74216859942379, "targetAvailable": 0}, {"name": "solid waste treatment other", "score": 61.62367954120173, "targetAvailable": 0}, {"name": "solid waste treatment open dump", "score": 40.65634890263279, "targetAvailable": 0}], "score": 49.5678562543654, "targetAvailable": 0}, {"name": "environment quality", "children": [{"name": "emf exposure", "score": 56.60672770912961, "targetAvailable": 0}, {"name": "noise exposure", "score": 45.15672975602491, "targetAvailable": 0}], "score": 50.881728732577265, "targetAvailable": 0}, {"name": "public space and nature", "children": [{"name": "green areas", "score": 49.98656575521654, "targetAvailable": 0}, {"name": "green area accessibility", "score": 39.32454751687818, "targetAvailable": 0}, {"name": "protected areas", "score": 48.584968907317915, "targetAvailable": 0}, {"name": "recreational facilities", "score": 58.619786424000814, "targetAvailable": 0}], "score": 49.12896715085336, "targetAvailable": 0}, {"name": "energy", "children": [{"name": "renewable energy consumption", "score": 48.00480889377306, "targetAvailable": 0}, {"name": "electricity consumption", "score": 53.49640454760884, "targetAvailable": 0}, {"name": "residential thermal energy consumption", "score": 46.60963165489087, "targetAvailable": 0}, {"name": "public building energy consumption", "score": 45.661999760800285, "targetAvailable": 0}], "score": 48.44321121426825, "targetAvailable": 0}], "score": 49.83807905417266, "targetAvailable": 0}], "score": 49.96911097167365, "targetAvailable": 0}