{"name": "Asker", "children": [{"name": "society", "children": [{"name": "education", "children": [{"name": "students ict access", "score": 69.53737740290705, "targetAvailable": 0}, {"name": "school enrollment", "score": 3.4605995618735563, "targetAvailable": 0}, {"name": "higher education degrees", "score": 12.075377376729834, "targetAvailable": 0}, {"name": "adult literacy", "score": 54.07382122811523, "targetAvailable": 0}], "targetAvailable": 0, "score": 34.786793892406415}, {"name": "health", "children": [{"name": "electronic health records", "score": 25.882134529551813, "targetAvailable": 0}, {"name": "life expectancy", "score": 25.796217815168976, "targetAvailable": 0}, {"name": "maternal mortality rate", "score": 50.19495239820445, "targetAvailable": 0}, {"name": "doctors", "score": 31.20468455978761, "targetAvailable": 0}, {"name": "health insurance coverage", "score": 23.087318158744008, "targetAvailable": 0}, {"name": "in-patient hospital beds", "score": 86.30390188005052, "targetAvailable": 0}], "targetAvailable": 0, "score": 40.41153489025123}, {"name": "culture", "children": [{"name": "cultural expenditure", "score": 21.769616242045576, "targetAvailable": 0}, {"name": "cultural infrastructure", "score": 82.15791487542779, "targetAvailable": 0}], "targetAvailable": 0, "score": 51.96376555873668}, {"name": "housing", "children": [{"name": "informal settlements", "score": 43.79360802819296, "targetAvailable": 0}, {"name": "housing expenditure", "score": 75.70912596138297, "targetAvailable": 0}], "targetAvailable": 0, "score": 59.751366994787965}, {"name": "social inclusion", "children": [{"name": "gender income equity", "score": 86.57296229700955, "targetAvailable": 0}, {"name": "gini coefficient", "score": 64.0974749022363, "targetAvailable": 0}, {"name": "poverty", "score": 55.90275746409286, "targetAvailable": 0}, {"name": "voter participation", "score": 36.69494667920229, "targetAvailable": 0}, {"name": "child care availability", "score": 86.4125406549881, "targetAvailable": 0}], "targetAvailable": 0, "score": 65.93613639950583}, {"name": "safety", "children": [{"name": "natural disaster related deaths", "score": 6.887109514861633, "targetAvailable": 0}, {"name": "disaster related economic losses", "score": 89.20535081196319, "targetAvailable": 0}, {"name": "resilience plans", "score": 7.941711428586052, "targetAvailable": 0}, {"name": "at risk population", "score": 22.169404738792874, "targetAvailable": 0}, {"name": "Emergency service response time", "score": 82.24694184934309, "targetAvailable": 0}, {"name": "police service", "score": 35.28515885573379, "targetAvailable": 0}, {"name": "fire service", "score": 25.22308966169128, "targetAvailable": 0}, {"name": "violent crime rate", "score": 21.689311436255075, "targetAvailable": 0}, {"name": "transportation fatalities", "score": 56.25166595579268, "targetAvailable": 0}], "targetAvailable": 0, "score": 38.5444160281133}, {"name": "food security", "children": [{"name": "local food production", "score": 62.341762956459625, "targetAvailable": 0}], "targetAvailable": 0, "score": 62.341762956459625}], "targetAvailable": 0, "score": 50.53368238860872}, {"name": "economy", "children": [{"name": "ict infrastructure", "children": [{"name": "household internet access", "score": 96.01950882835627, "targetAvailable": 0}, {"name": "fixed broadband subscriptions", "score": 32.67596657908002, "targetAvailable": 0}, {"name": "wireless broadband subscription", "score": 29.322539730250686, "targetAvailable": 0}, {"name": "wireless broadband coverage 3G", "score": 86.21197780161613, "targetAvailable": 0}, {"name": "wireless broadband coverage 4G", "score": 36.08903109397995, "targetAvailable": 0}, {"name": "availability of wifi in public areas", "score": 92.42998493572657, "targetAvailable": 0}], "targetAvailable": 0, "score": 62.12483482816827}, {"name": "water and sanitation", "children": [{"name": "smart water meters", "score": 22.248091726697538, "targetAvailable": 0}, {"name": "water supply ict monitoring", "score": 47.608786542456436, "targetAvailable": 0}, {"name": "basic water supply", "score": 16.801074006941175, "targetAvailable": 0}, {"name": "potable water supply", "score": 30.422401463196746, "targetAvailable": 0}, {"name": "water supply loss", "score": 76.2302307151322, "targetAvailable": 0}, {"name": "wastewater collection", "score": 8.491583047787676, "targetAvailable": 0}, {"name": "household sanitation", "score": 51.916942415866615, "targetAvailable": 0}], "targetAvailable": 0, "score": 36.24558713115406}, {"name": "drainage", "children": [{"name": "drainage / storm water system ict monitoring", "score": 82.79770186545773, "targetAvailable": 0}], "targetAvailable": 0, "score": 82.79770186545773}, {"name": "electricity supply", "children": [{"name": "smart electricity meters", "score": 86.44623261591545, "targetAvailable": 0}, {"name": "electricity supply ict monitoring", "score": 89.03200268155128, "targetAvailable": 0}, {"name": "demand response penetration", "score": 89.43230712012159, "targetAvailable": 0}, {"name": "electricity system outage frequency", "score": 85.81125106984975, "targetAvailable": 0}, {"name": "electricity system outage time", "score": 16.648058030288094, "targetAvailable": 0}, {"name": "access to electricity", "score": 10.030576674119295, "targetAvailable": 0}], "targetAvailable": 0, "score": 62.900071365307575}, {"name": "transport", "children": [{"name": "dynamic public transport information", "score": 47.135342642502366, "targetAvailable": 0}, {"name": "traffic monitoring", "score": 30.20808520184268, "targetAvailable": 0}, {"name": "intersection control", "score": 74.57110134983458, "targetAvailable": 0}, {"name": "public transit network", "score": 63.827480899631404, "targetAvailable": 0}, {"name": "public transit network convenience", "score": 15.096167794698523, "targetAvailable": 0}, {"name": "bicycle network", "score": 88.24817609767629, "targetAvailable": 0}, {"name": "transportation mode share private vehicles", "score": 29.77099197605748, "targetAvailable": 0}, {"name": "transportation mode share public transport", "score": 47.10314608859352, "targetAvailable": 0}, {"name": "transportation mode share walking", "score": 75.97031026271966, "targetAvailable": 0}, {"name": "transportation mode share cycling", "score": 54.59804102245825, "targetAvailable": 0}, {"name": "transportation mode share paratransport", "score": 76.41946998335808, "targetAvailable": 0}, {"name": "travel time index", "score": 35.1956205416944, "targetAvailable": 0}, {"name": "shared bicycles", "score": 35.59712917559912, "targetAvailable": 0}, {"name": "shared vehicles", "score": 77.02155881471995, "targetAvailable": 0}, {"name": "low-carbon emission vehicles", "score": 71.86654565973507, "targetAvailable": 0}], "targetAvailable": 0, "score": 54.84194450074142}, {"name": "public service", "children": [{"name": "open data sets published", "score": 48.34011789586097, "targetAvailable": 0}, {"name": "open data sets %", "score": 17.8383509311266, "targetAvailable": 0}, {"name": "e-government", "score": 73.67314169524798, "targetAvailable": 0}, {"name": "public sector e-procurement", "score": 59.32909079750671, "targetAvailable": 0}], "targetAvailable": 0, "score": 49.79517532993556}, {"name": "innovation", "children": [{"name": "R&D expenditure", "score": 0.29250631732822274, "targetAvailable": 0}, {"name": "patents", "score": 74.11223875247256, "targetAvailable": 0}, {"name": "small and medium-sized enterprises", "score": 84.43515992087045, "targetAvailable": 0}], "targetAvailable": 0, "score": 52.94663499689042}, {"name": "employment", "children": [{"name": "unemployment rate", "score": 53.50202378686648, "targetAvailable": 0}, {"name": "youth unemployment rate", "score": 69.0421803152666, "targetAvailable": 0}, {"name": "tourism industry employment", "score": 22.960331589821504, "targetAvailable": 0}, {"name": "ict industry employment", "score": 50.47141612445617, "targetAvailable": 0}], "targetAvailable": 0, "score": 48.993987954102685}, {"name": "waste", "children": [{"name": "solid waste collection", "score": 59.44430938573597, "targetAvailable": 0}], "targetAvailable": 0, "score": 59.44430938573597}, {"name": "buildings", "children": [{"name": "public building sustainability", "score": 75.11101411667967, "targetAvailable": 0}, {"name": "integrated building management systems", "score": 20.07855692905943, "targetAvailable": 0}], "targetAvailable": 0, "score": 47.59478552286955}, {"name": "urban planning", "children": [{"name": "pedestrian infrastructure", "score": 19.5070561763209, "targetAvailable": 0}, {"name": "urban development and spatial planning", "score": 71.448372340767, "targetAvailable": 0}], "targetAvailable": 0, "score": 45.47771425854395}], "targetAvailable": 0, "score": 54.83297701262793}, {"name": "environment", "children": [{"name": "air quality", "children": [{"name": "air pollution PM2.5", "score": 36.55051037019206, "targetAvailable": 0}, {"name": "air pollution PM10", "score": 20.865125321549016, "targetAvailable": 0}, {"name": "air pollution NO2", "score": 43.3976487924609, "targetAvailable": 0}, {"name": "air pollution SO2", "score": 24.30171079839618, "targetAvailable": 0}, {"name": "air pollution O3", "score": 35.10795283707634, "targetAvailable": 0}, {"name": "ghg emissions", "score": 37.15176872957902, "targetAvailable": 0}], "targetAvailable": 0, "score": 32.89578614154225}, {"name": "waster and sanitation", "children": [{"name": "drinking water quality", "score": 89.72105331741555, "targetAvailable": 0}, {"name": "water consumption", "score": 60.11491291569493, "targetAvailable": 0}, {"name": "fresh water consumption", "score": 27.8173697304407, "targetAvailable": 0}, {"name": "wastewater treated primary", "score": 45.00992638915764, "targetAvailable": 0}, {"name": "wastewater treated secondary", "score": 73.78100810200941, "targetAvailable": 0}, {"name": "wastewater treated tertiary", "score": 43.628537578101664, "targetAvailable": 0}], "targetAvailable": 0, "score": 56.67880133880331}, {"name": "environmental waste", "children": [{"name": "solid waste treatment landfill", "score": 32.80308202850005, "targetAvailable": 0}, {"name": "solid waste treatment burnt", "score": 54.20588248705486, "targetAvailable": 0}, {"name": "solid waste treatment incinerated", "score": 54.77336853262506, "targetAvailable": 0}, {"name": "solid waste treatment recycled", "score": 14.616403071273343, "targetAvailable": 0}, {"name": "solid waste treatment other", "score": 6.103021409099075, "targetAvailable": 0}, {"name": "solid waste treatment open dump", "score": 66.88931623317129, "targetAvailable": 0}], "targetAvailable": 0, "score": 38.23184562695395}, {"name": "environment quality", "children": [{"name": "emf exposure", "score": 23.743730376628235, "targetAvailable": 0}, {"name": "noise exposure", "score": 46.70925149568356, "targetAvailable": 0}], "targetAvailable": 0, "score": 35.2264909361559}, {"name": "public space and nature", "children": [{"name": "green areas", "score": 23.45330689021049, "targetAvailable": 0}, {"name": "green area accessibility", "score": 7.466178556339342, "targetAvailable": 0}, {"name": "protected areas", "score": 66.49166175674317, "targetAvailable": 0}, {"name": "recreational facilities", "score": 82.88053529671049, "targetAvailable": 0}], "targetAvailable": 0, "score": 45.072920625000876}, {"name": "energy", "children": [{"name": "renewable energy consumption", "score": 84.28382686330463, "targetAvailable": 0}, {"name": "electricity consumption", "score": 61.36431725695163, "targetAvailable": 0}, {"name": "residential thermal energy consumption", "score": 80.99157215941143, "targetAvailable": 0}, {"name": "public building energy consumption", "score": 35.02669560660557, "targetAvailable": 0}], "targetAvailable": 0, "score": 65.41660297156832}], "targetAvailable": 0, "score": 45.58707460667077}], "targetAvailable": 0, "score": 50.31791133596914}