{"name": "Haugesund", "children": [{"name": "society", "children": [{"name": "education", "children": [{"name": "students ict access", "score": 23.831816662140714, "targetAvailable": 0}, {"name": "school enrollment", "score": 92.31035913177672, "targetAvailable": 0}, {"name": "higher education degrees", "score": 55.580038061546425, "targetAvailable": 0}, {"name": "adult literacy", "score": 7.754208966814735, "targetAvailable": 0}], "targetAvailable": 0, "score": 44.869105705569645}, {"name": "health", "children": [{"name": "electronic health records", "score": 19.174963364029164, "targetAvailable": 0}, {"name": "life expectancy", "score": 91.56781884342567, "targetAvailable": 0}, {"name": "maternal mortality rate", "score": 27.802179835779974, "targetAvailable": 0}, {"name": "doctors", "score": 10.88231486877117, "targetAvailable": 0}, {"name": "health insurance coverage", "score": 72.12388840549056, "targetAvailable": 0}, {"name": "in-patient hospital beds", "score": 87.9059535512233, "targetAvailable": 0}], "targetAvailable": 0, "score": 51.57618647811998}, {"name": "culture", "children": [{"name": "cultural expenditure", "score": 16.044613935085838, "targetAvailable": 0}, {"name": "cultural infrastructure", "score": 35.3342203550611, "targetAvailable": 0}], "targetAvailable": 0, "score": 25.68941714507347}, {"name": "housing", "children": [{"name": "informal settlements", "score": 57.39823461725941, "targetAvailable": 0}, {"name": "housing expenditure", "score": 30.088435280235316, "targetAvailable": 0}], "targetAvailable": 0, "score": 43.74333494874736}, {"name": "social inclusion", "children": [{"name": "gender income equity", "score": 13.629304018493293, "targetAvailable": 0}, {"name": "gini coefficient", "score": 25.895680076938078, "targetAvailable": 0}, {"name": "poverty", "score": 12.857931498629293, "targetAvailable": 0}, {"name": "voter participation", "score": 49.181516366122814, "targetAvailable": 0}, {"name": "child care availability", "score": 26.74500390669101, "targetAvailable": 0}], "targetAvailable": 0, "score": 25.661887173374897}, {"name": "safety", "children": [{"name": "natural disaster related deaths", "score": 11.876572082010362, "targetAvailable": 0}, {"name": "disaster related economic losses", "score": 61.60264243425571, "targetAvailable": 0}, {"name": "resilience plans", "score": 24.165728586724544, "targetAvailable": 0}, {"name": "at risk population", "score": 38.23342005472369, "targetAvailable": 0}, {"name": "Emergency service response time", "score": 2.620082553058667, "targetAvailable": 0}, {"name": "police service", "score": 64.52349015506475, "targetAvailable": 0}, {"name": "fire service", "score": 60.702189788238435, "targetAvailable": 0}, {"name": "violent crime rate", "score": 6.162865810491502, "targetAvailable": 0}, {"name": "transportation fatalities", "score": 72.80624787263486, "targetAvailable": 0}], "targetAvailable": 0, "score": 38.07702659302251}, {"name": "food security", "children": [{"name": "local food production", "score": 19.88811856941779, "targetAvailable": 0}], "targetAvailable": 0, "score": 19.88811856941779}], "targetAvailable": 0, "score": 35.64358237333224}, {"name": "economy", "children": [{"name": "ict infrastructure", "children": [{"name": "household internet access", "score": 35.45305026593232, "targetAvailable": 0}, {"name": "fixed broadband subscriptions", "score": 93.55516886873575, "targetAvailable": 0}, {"name": "wireless broadband subscription", "score": 67.89484080621367, "targetAvailable": 0}, {"name": "wireless broadband coverage 3G", "score": 13.91033684546773, "targetAvailable": 0}, {"name": "wireless broadband coverage 4G", "score": 95.09299931210357, "targetAvailable": 0}, {"name": "availability of wifi in public areas", "score": 5.66319080835539, "targetAvailable": 0}], "targetAvailable": 0, "score": 51.92826448446808}, {"name": "water and sanitation", "children": [{"name": "smart water meters", "score": 96.1579477312276, "targetAvailable": 0}, {"name": "water supply ict monitoring", "score": 24.449559235231067, "targetAvailable": 0}, {"name": "basic water supply", "score": 98.17688532209772, "targetAvailable": 0}, {"name": "potable water supply", "score": 62.80674607019695, "targetAvailable": 0}, {"name": "water supply loss", "score": 53.31334246627447, "targetAvailable": 0}, {"name": "wastewater collection", "score": 46.30428405274911, "targetAvailable": 0}, {"name": "household sanitation", "score": 5.908668275513007, "targetAvailable": 0}], "targetAvailable": 0, "score": 55.30249045046998}, {"name": "drainage", "children": [{"name": "drainage / storm water system ict monitoring", "score": 86.07330570822421, "targetAvailable": 0}], "targetAvailable": 0, "score": 86.07330570822421}, {"name": "electricity supply", "children": [{"name": "smart electricity meters", "score": 73.91222714654748, "targetAvailable": 0}, {"name": "electricity supply ict monitoring", "score": 95.80699878384867, "targetAvailable": 0}, {"name": "demand response penetration", "score": 78.33082689688882, "targetAvailable": 0}, {"name": "electricity system outage frequency", "score": 72.70732426131742, "targetAvailable": 0}, {"name": "electricity system outage time", "score": 38.208730485566214, "targetAvailable": 0}, {"name": "access to electricity", "score": 78.92379535461225, "targetAvailable": 0}], "targetAvailable": 0, "score": 72.98165048813014}, {"name": "transport", "children": [{"name": "dynamic public transport information", "score": 82.35653862874014, "targetAvailable": 0}, {"name": "traffic monitoring", "score": 50.14746051030078, "targetAvailable": 0}, {"name": "intersection control", "score": 8.763060903395703, "targetAvailable": 0}, {"name": "public transit network", "score": 59.255964074181634, "targetAvailable": 0}, {"name": "public transit network convenience", "score": 60.53463807551985, "targetAvailable": 0}, {"name": "bicycle network", "score": 99.91274004013518, "targetAvailable": 0}, {"name": "transportation mode share private vehicles", "score": 91.35300421904863, "targetAvailable": 0}, {"name": "transportation mode share public transport", "score": 58.36260659695481, "targetAvailable": 0}, {"name": "transportation mode share walking", "score": 57.03367878531507, "targetAvailable": 0}, {"name": "transportation mode share cycling", "score": 17.411158355310043, "targetAvailable": 0}, {"name": "transportation mode share paratransport", "score": 99.18578340783321, "targetAvailable": 0}, {"name": "travel time index", "score": 87.94803939424509, "targetAvailable": 0}, {"name": "shared bicycles", "score": 96.02455643324748, "targetAvailable": 0}, {"name": "shared vehicles", "score": 34.928560376808235, "targetAvailable": 0}, {"name": "low-carbon emission vehicles", "score": 75.51079400511958, "targetAvailable": 0}], "targetAvailable": 0, "score": 65.2485722537437}, {"name": "public service", "children": [{"name": "open data sets published", "score": 52.75040296659533, "targetAvailable": 0}, {"name": "open data sets %", "score": 75.51639128238541, "targetAvailable": 0}, {"name": "e-government", "score": 50.34732261004763, "targetAvailable": 0}, {"name": "public sector e-procurement", "score": 55.488205932417124, "targetAvailable": 0}], "targetAvailable": 0, "score": 58.52558069786137}, {"name": "innovation", "children": [{"name": "R&D expenditure", "score": 95.34997991249523, "targetAvailable": 0}, {"name": "patents", "score": 25.150210846488964, "targetAvailable": 0}, {"name": "small and medium-sized enterprises", "score": 93.85788276196382, "targetAvailable": 0}], "targetAvailable": 0, "score": 71.45269117364934}, {"name": "employment", "children": [{"name": "unemployment rate", "score": 14.517906325995057, "targetAvailable": 0}, {"name": "youth unemployment rate", "score": 67.20271387931423, "targetAvailable": 0}, {"name": "tourism industry employment", "score": 84.87218404549154, "targetAvailable": 0}, {"name": "ict industry employment", "score": 87.7132181764701, "targetAvailable": 0}], "targetAvailable": 0, "score": 63.57650560681773}, {"name": "waste", "children": [{"name": "solid waste collection", "score": 77.67502664815429, "targetAvailable": 0}], "targetAvailable": 0, "score": 77.67502664815429}, {"name": "buildings", "children": [{"name": "public building sustainability", "score": 9.995441910858705, "targetAvailable": 0}, {"name": "integrated building management systems", "score": 28.08229161688729, "targetAvailable": 0}], "targetAvailable": 0, "score": 19.038866763872996}, {"name": "urban planning", "children": [{"name": "pedestrian infrastructure", "score": 8.9718172736855, "targetAvailable": 0}, {"name": "urban development and spatial planning", "score": 30.229737617687046, "targetAvailable": 0}], "targetAvailable": 0, "score": 19.600777445686273}], "targetAvailable": 0, "score": 58.30943015646164}, {"name": "environment", "children": [{"name": "air quality", "children": [{"name": "air pollution PM2.5", "score": 12.41066912781893, "targetAvailable": 0}, {"name": "air pollution PM10", "score": 5.005585662105005, "targetAvailable": 0}, {"name": "air pollution NO2", "score": 10.081091413075072, "targetAvailable": 0}, {"name": "air pollution SO2", "score": 69.69164270260467, "targetAvailable": 0}, {"name": "air pollution O3", "score": 49.08651825086696, "targetAvailable": 0}, {"name": "ghg emissions", "score": 51.0910618419637, "targetAvailable": 0}], "targetAvailable": 0, "score": 32.894428166405724}, {"name": "waster and sanitation", "children": [{"name": "drinking water quality", "score": 69.13248778660603, "targetAvailable": 0}, {"name": "water consumption", "score": 79.03438033591614, "targetAvailable": 0}, {"name": "fresh water consumption", "score": 14.065857576293105, "targetAvailable": 0}, {"name": "wastewater treated primary", "score": 33.50178881502225, "targetAvailable": 0}, {"name": "wastewater treated secondary", "score": 4.975893857973446, "targetAvailable": 0}, {"name": "wastewater treated tertiary", "score": 88.46203938183027, "targetAvailable": 0}], "targetAvailable": 0, "score": 48.1954079589402}, {"name": "environmental waste", "children": [{"name": "solid waste treatment landfill", "score": 27.19138599527988, "targetAvailable": 0}, {"name": "solid waste treatment burnt", "score": 45.25275430708711, "targetAvailable": 0}, {"name": "solid waste treatment incinerated", "score": 86.0297611636654, "targetAvailable": 0}, {"name": "solid waste treatment recycled", "score": 7.16429632322323, "targetAvailable": 0}, {"name": "solid waste treatment other", "score": 46.305515567433005, "targetAvailable": 0}, {"name": "solid waste treatment open dump", "score": 38.988370842840624, "targetAvailable": 0}], "targetAvailable": 0, "score": 41.82201403325487}, {"name": "environment quality", "children": [{"name": "emf exposure", "score": 25.72660449217271, "targetAvailable": 0}, {"name": "noise exposure", "score": 19.371054931781206, "targetAvailable": 0}], "targetAvailable": 0, "score": 22.548829711976957}, {"name": "public space and nature", "children": [{"name": "green areas", "score": 48.72020018771535, "targetAvailable": 0}, {"name": "green area accessibility", "score": 18.78635364169806, "targetAvailable": 0}, {"name": "protected areas", "score": 48.64109744407653, "targetAvailable": 0}, {"name": "recreational facilities", "score": 3.2554751109380775, "targetAvailable": 0}], "targetAvailable": 0, "score": 29.850781596107005}, {"name": "energy", "children": [{"name": "renewable energy consumption", "score": 88.01098612492233, "targetAvailable": 0}, {"name": "electricity consumption", "score": 94.59074962944752, "targetAvailable": 0}, {"name": "residential thermal energy consumption", "score": 8.123069088323852, "targetAvailable": 0}, {"name": "public building energy consumption", "score": 9.44664183786803, "targetAvailable": 0}], "targetAvailable": 0, "score": 50.04286167014043}], "targetAvailable": 0, "score": 37.55905385613753}], "targetAvailable": 0, "score": 43.83735546197713}