{"name": "Haugesund", "children": [{"name": "society", "children": [{"name": "education", "children": [{"name": "students ict access", "score": 13.315451338430295, "targetAvailable": 0}, {"name": "school enrollment", "score": 0.7211104620580611, "targetAvailable": 0}, {"name": "higher education degrees", "score": 31.89618325049768, "targetAvailable": 0}, {"name": "adult literacy", "score": 96.53725792655757, "targetAvailable": 0}], "targetAvailable": 0, "score": 35.6175007443859}, {"name": "health", "children": [{"name": "electronic health records", "score": 37.678959976516815, "targetAvailable": 0}, {"name": "life expectancy", "score": 47.921695676691115, "targetAvailable": 0}, {"name": "maternal mortality rate", "score": 36.26090071386629, "targetAvailable": 0}, {"name": "doctors", "score": 95.87147481488427, "targetAvailable": 0}, {"name": "health insurance coverage", "score": 34.06460317795476, "targetAvailable": 0}, {"name": "in-patient hospital beds", "score": 51.53720029312131, "targetAvailable": 0}], "targetAvailable": 0, "score": 50.55580577550575}, {"name": "culture", "children": [{"name": "cultural expenditure", "score": 69.68721000756074, "targetAvailable": 0}, {"name": "cultural infrastructure", "score": 99.78082128723364, "targetAvailable": 0}], "targetAvailable": 0, "score": 84.73401564739719}, {"name": "housing", "children": [{"name": "informal settlements", "score": 17.815679251364248, "targetAvailable": 0}, {"name": "housing expenditure", "score": 98.17726804920125, "targetAvailable": 0}], "targetAvailable": 0, "score": 57.996473650282745}, {"name": "social inclusion", "children": [{"name": "gender income equity", "score": 63.675358946035175, "targetAvailable": 0}, {"name": "gini coefficient", "score": 65.14529740940736, "targetAvailable": 0}, {"name": "poverty", "score": 97.1272099010878, "targetAvailable": 0}, {"name": "voter participation", "score": 70.45958283741038, "targetAvailable": 0}, {"name": "child care availability", "score": 35.460821237739104, "targetAvailable": 0}], "targetAvailable": 0, "score": 66.37365406633596}, {"name": "safety", "children": [{"name": "natural disaster related deaths", "score": 88.32566712303235, "targetAvailable": 0}, {"name": "disaster related economic losses", "score": 12.854217855366512, "targetAvailable": 0}, {"name": "resilience plans", "score": 76.73370410198011, "targetAvailable": 0}, {"name": "at risk population", "score": 53.00778963478879, "targetAvailable": 0}, {"name": "Emergency service response time", "score": 43.13389403959431, "targetAvailable": 0}, {"name": "police service", "score": 82.91694059777195, "targetAvailable": 0}, {"name": "fire service", "score": 40.94925940512761, "targetAvailable": 0}, {"name": "violent crime rate", "score": 81.28375661777748, "targetAvailable": 0}, {"name": "transportation fatalities", "score": 77.3710759489326, "targetAvailable": 0}], "targetAvailable": 0, "score": 61.841811702707965}, {"name": "food security", "children": [{"name": "local food production", "score": 15.012866070304886, "targetAvailable": 0}], "targetAvailable": 0, "score": 15.012866070304886}], "targetAvailable": 0, "score": 53.161732522417196}, {"name": "economy", "children": [{"name": "ict infrastructure", "children": [{"name": "household internet access", "score": 62.888672669136504, "targetAvailable": 0}, {"name": "fixed broadband subscriptions", "score": 22.44706074935018, "targetAvailable": 0}, {"name": "wireless broadband subscription", "score": 70.66634149592724, "targetAvailable": 0}, {"name": "wireless broadband coverage 3G", "score": 50.20303749593986, "targetAvailable": 0}, {"name": "wireless broadband coverage 4G", "score": 73.80979894729369, "targetAvailable": 0}, {"name": "availability of wifi in public areas", "score": 44.81326285741377, "targetAvailable": 0}], "targetAvailable": 0, "score": 54.13802903584354}, {"name": "water and sanitation", "children": [{"name": "smart water meters", "score": 55.95728650439848, "targetAvailable": 0}, {"name": "water supply ict monitoring", "score": 29.33250803128471, "targetAvailable": 0}, {"name": "basic water supply", "score": 80.99533778099588, "targetAvailable": 0}, {"name": "potable water supply", "score": 32.32589956789741, "targetAvailable": 0}, {"name": "water supply loss", "score": 72.13489912633476, "targetAvailable": 0}, {"name": "wastewater collection", "score": 9.425723986941604, "targetAvailable": 0}, {"name": "household sanitation", "score": 68.10178181636105, "targetAvailable": 0}], "targetAvailable": 0, "score": 49.75334811631627}, {"name": "drainage", "children": [{"name": "drainage / storm water system ict monitoring", "score": 90.44326285081999, "targetAvailable": 0}], "targetAvailable": 0, "score": 90.44326285081999}, {"name": "electricity supply", "children": [{"name": "smart electricity meters", "score": 6.379823286887987, "targetAvailable": 0}, {"name": "electricity supply ict monitoring", "score": 39.19421409641084, "targetAvailable": 0}, {"name": "demand response penetration", "score": 77.41962364350083, "targetAvailable": 0}, {"name": "electricity system outage frequency", "score": 40.8949610745619, "targetAvailable": 0}, {"name": "electricity system outage time", "score": 23.999130269874737, "targetAvailable": 0}, {"name": "access to electricity", "score": 16.57691422441251, "targetAvailable": 0}], "targetAvailable": 0, "score": 34.07744443260814}, {"name": "transport", "children": [{"name": "dynamic public transport information", "score": 69.46642178679575, "targetAvailable": 0}, {"name": "traffic monitoring", "score": 14.066797978244649, "targetAvailable": 0}, {"name": "intersection control", "score": 19.438998054381972, "targetAvailable": 0}, {"name": "public transit network", "score": 88.07093128827668, "targetAvailable": 0}, {"name": "public transit network convenience", "score": 49.59453931055785, "targetAvailable": 0}, {"name": "bicycle network", "score": 88.65031719772368, "targetAvailable": 0}, {"name": "transportation mode share private vehicles", "score": 45.83863011568214, "targetAvailable": 0}, {"name": "transportation mode share public transport", "score": 74.96324229722174, "targetAvailable": 0}, {"name": "transportation mode share walking", "score": 37.119161962105565, "targetAvailable": 0}, {"name": "transportation mode share cycling", "score": 63.85426960899665, "targetAvailable": 0}, {"name": "transportation mode share paratransport", "score": 58.64439975509875, "targetAvailable": 0}, {"name": "travel time index", "score": 48.98430679507892, "targetAvailable": 0}, {"name": "shared bicycles", "score": 93.85923106127012, "targetAvailable": 0}, {"name": "shared vehicles", "score": 96.06345387073434, "targetAvailable": 0}, {"name": "low-carbon emission vehicles", "score": 32.0755913880051, "targetAvailable": 0}], "targetAvailable": 0, "score": 58.712686164678274}, {"name": "public service", "children": [{"name": "open data sets published", "score": 57.40648064099897, "targetAvailable": 0}, {"name": "open data sets %", "score": 45.60076769946713, "targetAvailable": 0}, {"name": "e-government", "score": 96.12594738262483, "targetAvailable": 0}, {"name": "public sector e-procurement", "score": 3.2977355946011033, "targetAvailable": 0}], "targetAvailable": 0, "score": 50.60773282942301}, {"name": "innovation", "children": [{"name": "R&D expenditure", "score": 95.51105853738143, "targetAvailable": 0}, {"name": "patents", "score": 86.13420320402194, "targetAvailable": 0}, {"name": "small and medium-sized enterprises", "score": 9.542590280038421, "targetAvailable": 0}], "targetAvailable": 0, "score": 63.729284007147264}, {"name": "employment", "children": [{"name": "unemployment rate", "score": 25.074600099683053, "targetAvailable": 0}, {"name": "youth unemployment rate", "score": 39.71892496974861, "targetAvailable": 0}, {"name": "tourism industry employment", "score": 47.5708855666571, "targetAvailable": 0}, {"name": "ict industry employment", "score": 45.649587378081705, "targetAvailable": 0}], "targetAvailable": 0, "score": 39.50349950354261}, {"name": "waste", "children": [{"name": "solid waste collection", "score": 37.1846598060253, "targetAvailable": 0}], "targetAvailable": 0, "score": 37.1846598060253}, {"name": "buildings", "children": [{"name": "public building sustainability", "score": 49.5264655375877, "targetAvailable": 0}, {"name": "integrated building management systems", "score": 16.985101186439387, "targetAvailable": 0}], "targetAvailable": 0, "score": 33.255783362013545}, {"name": "urban planning", "children": [{"name": "pedestrian infrastructure", "score": 14.217477238309762, "targetAvailable": 0}, {"name": "urban development and spatial planning", "score": 12.338672877186008, "targetAvailable": 0}], "targetAvailable": 0, "score": 13.278075057747884}], "targetAvailable": 0, "score": 47.69852774237871}, {"name": "environment", "children": [{"name": "air quality", "children": [{"name": "air pollution PM2.5", "score": 1.753894092832009, "targetAvailable": 0}, {"name": "air pollution PM10", "score": 15.425771184104365, "targetAvailable": 0}, {"name": "air pollution NO2", "score": 45.44801302701963, "targetAvailable": 0}, {"name": "air pollution SO2", "score": 25.475290396063322, "targetAvailable": 0}, {"name": "air pollution O3", "score": 22.789559901183733, "targetAvailable": 0}, {"name": "ghg emissions", "score": 57.76441133315646, "targetAvailable": 0}], "targetAvailable": 0, "score": 28.10948998905992}, {"name": "waster and sanitation", "children": [{"name": "drinking water quality", "score": 93.9572344190974, "targetAvailable": 0}, {"name": "water consumption", "score": 57.546009517947695, "targetAvailable": 0}, {"name": "fresh water consumption", "score": 45.28389013200198, "targetAvailable": 0}, {"name": "wastewater treated primary", "score": 31.00290285593149, "targetAvailable": 0}, {"name": "wastewater treated secondary", "score": 30.316459584787324, "targetAvailable": 0}, {"name": "wastewater treated tertiary", "score": 54.24480736416007, "targetAvailable": 0}], "targetAvailable": 0, "score": 52.05855064565433}, {"name": "environmental waste", "children": [{"name": "solid waste treatment landfill", "score": 38.82646893078597, "targetAvailable": 0}, {"name": "solid waste treatment burnt", "score": 70.05088060129236, "targetAvailable": 0}, {"name": "solid waste treatment incinerated", "score": 52.453158498833496, "targetAvailable": 0}, {"name": "solid waste treatment recycled", "score": 68.63061011039507, "targetAvailable": 0}, {"name": "solid waste treatment other", "score": 44.990734602398696, "targetAvailable": 0}, {"name": "solid waste treatment open dump", "score": 27.85781338551976, "targetAvailable": 0}], "targetAvailable": 0, "score": 50.46827768820422}, {"name": "environment quality", "children": [{"name": "emf exposure", "score": 19.091682135158084, "targetAvailable": 0}, {"name": "noise exposure", "score": 85.2935608576877, "targetAvailable": 0}], "targetAvailable": 0, "score": 52.19262149642289}, {"name": "public space and nature", "children": [{"name": "green areas", "score": 55.5254166649529, "targetAvailable": 0}, {"name": "green area accessibility", "score": 50.45105483637532, "targetAvailable": 0}, {"name": "protected areas", "score": 72.90026073413198, "targetAvailable": 0}, {"name": "recreational facilities", "score": 24.490869021031493, "targetAvailable": 0}], "targetAvailable": 0, "score": 50.841900314122924}, {"name": "energy", "children": [{"name": "renewable energy consumption", "score": 72.85173782632972, "targetAvailable": 0}, {"name": "electricity consumption", "score": 83.87879169412335, "targetAvailable": 0}, {"name": "residential thermal energy consumption", "score": 85.89201245394425, "targetAvailable": 0}, {"name": "public building energy consumption", "score": 18.934829452199686, "targetAvailable": 0}], "targetAvailable": 0, "score": 65.38934285664925}], "targetAvailable": 0, "score": 49.84336383168559}], "targetAvailable": 0, "score": 50.23454136549383}